Workbook

Sheet Dashboard
B2: Sales Performance Dashboard
B3: Author: Parthasarathi S | Oracle SQL Developer & Data Analyst
B6: Total Revenue (₹) | D6: Total Profit (₹) | F6: Profit Margin | H6: Total Orders
B7: =SUM(Raw_Data!H2:H91) -> 15469300 | D7: =SUM(Raw_Data!J2:J91) -> 4859521 | F7: =D7/B7 -> 0.31413968 | H7: =COUNTA(Raw_Data!A2:A91) -> 90
B10: Revenue & Profit by Region | G10: Revenue by Category
B11: Region | C11: Revenue (₹) | D11: Profit (₹) | E11: Orders | G11: Category | H11: Revenue (₹)
B12: North | C12: =SUMIFS(Raw_Data!$H$2:$H$91,Raw_Data!$C$2:$C$91,B12) -> 5587400 | D12: =SUMIFS(Raw_Data!$J$2:$J$91,Raw_Data!$C$2:$C$91,B12) -> 1765039 | E12: =COUNTIFS(Raw_Data!$C$2:$C$91,B12) -> 28 | G12: Computing | H12: =SUMPRODUCT((Raw_Data!$H$2:$H$91)*(VLOOKUP(Raw_Data!$E$2:$E$91,Lookup!$A$2:$B$7,2,FALSE())=G12)) -> 11935000
B13: South | C13: =SUMIFS(Raw_Data!$H$2:$H$91,Raw_Data!$C$2:$C$91,B13) -> 3136400 | D13: =SUMIFS(Raw_Data!$J$2:$J$91,Raw_Data!$C$2:$C$91,B13) -> 965757 | E13: =COUNTIFS(Raw_Data!$C$2:$C$91,B13) -> 18 | G13: Peripherals | H13: =SUMPRODUCT((Raw_Data!$H$2:$H$91)*(VLOOKUP(Raw_Data!$E$2:$E$91,Lookup!$A$2:$B$7,2,FALSE())=G13)) -> 2686300
B14: East | C14: =SUMIFS(Raw_Data!$H$2:$H$91,Raw_Data!$C$2:$C$91,B14) -> 3658900 | D14: =SUMIFS(Raw_Data!$J$2:$J$91,Raw_Data!$C$2:$C$91,B14) -> 1162788 | E14: =COUNTIFS(Raw_Data!$C$2:$C$91,B14) -> 20 | G14: Accessories | H14: =SUMPRODUCT((Raw_Data!$H$2:$H$91)*(VLOOKUP(Raw_Data!$E$2:$E$91,Lookup!$A$2:$B$7,2,FALSE())=G14)) -> 848000
B15: West | C15: =SUMIFS(Raw_Data!$H$2:$H$91,Raw_Data!$C$2:$C$91,B15) -> 3086600 | D15: =SUMIFS(Raw_Data!$J$2:$J$91,Raw_Data!$C$2:$C$91,B15) -> 965937 | E15: =COUNTIFS(Raw_Data!$C$2:$C$91,B15) -> 24

Sheet Raw_Data
A1: Order ID | B1: Date | C1: Region | D1: Sales Rep | E1: Product | F1: Units Sold | G1: Unit Price | H1: Revenue | I1: Cost | J1: Profit
A2: ORD-1000 | B2: 45821 | C2: North | D2: Arun | E2: Webcam | F2: 9 | G2: 2200 | H2: =F2*G2 -> 19800 | I2: =H2*VLOOKUP(E2,Lookup!$A$2:$C$7,3,FALSE()) -> 11880 | J2: =H2-I2 -> 7920
A3: ORD-1001 | B3: 45720 | C3: South | D3: Divya | E3: Webcam | F3: 4 | G3: 2200 | H3: =F3*G3 -> 8800 | I3: =H3*VLOOKUP(E3,Lookup!$A$2:$C$7,3,FALSE()) -> 5280 | J3: =H3-I3 -> 3520
A4: ORD-1002 | B4: 45831 | C4: North | D4: Ramesh | E4: Mouse | F4: 2 | G4: 650 | H4: =F4*G4 -> 1300 | I4: =H4*VLOOKUP(E4,Lookup!$A$2:$C$7,3,FALSE()) -> 650 | J4: =H4-I4 -> 650
A5: ORD-1003 | B5: 45665 | C5: North | D5: Divya | E5: Monitor | F5: 17 | G5: 9500 | H5: =F5*G5 -> 161500 | I5: =H5*VLOOKUP(E5,Lookup!$A$2:$C$7,3,FALSE()) -> 104975 | J5: =H5-I5 -> 56525
A6: ORD-1004 | B6: 45812 | C6: North | D6: Ramesh | E6: Monitor | F6: 23 | G6: 9500 | H6: =F6*G6 -> 218500 | I6: =H6*VLOOKUP(E6,Lookup!$A$2:$C$7,3,FALSE()) -> 142025 | J6: =H6-I6 -> 76475
A7: ORD-1005 | B7: 45824 | C7: West | D7: Divya | E7: Mouse | F7: 19 | G7: 650 | H7: =F7*G7 -> 12350 | I7: =H7*VLOOKUP(E7,Lookup!$A$2:$C$7,3,FALSE()) -> 6175 | J7: =H7-I7 -> 6175
A8: ORD-1006 | B8: 45729 | C8: North | D8: Divya | E8: Webcam | F8: 14 | G8: 2200 | H8: =F8*G8 -> 30800 | I8: =H8*VLOOKUP(E8,Lookup!$A$2:$C$7,3,FALSE()) -> 18480 | J8: =H8-I8 -> 12320
A9: ORD-1007 | B9: 45745 | C9: East | D9: Divya | E9: Monitor | F9: 25 | G9: 9500 | H9: =F9*G9 -> 237500 | I9: =H9*VLOOKUP(E9,Lookup!$A$2:$C$7,3,FALSE()) -> 154375 | J9: =H9-I9 -> 83125
A10: ORD-1008 | B10: 45744 | C10: North | D10: Arun | E10: Mouse | F10: 4 | G10: 650 | H10: =F10*G10 -> 2600 | I10: =H10*VLOOKUP(E10,Lookup!$A$2:$C$7,3,FALSE()) -> 1300 | J10: =H10-I10 -> 1300
A11: ORD-1009 | B11: 45749 | C11: East | D11: Ramesh | E11: Keyboard | F11: 2 | G11: 1200 | H11: =F11*G11 -> 2400 | I11: =H11*VLOOKUP(E11,Lookup!$A$2:$C$7,3,FALSE()) -> 1320 | J11: =H11-I11 -> 1080
A12: ORD-1010 | B12: 45844 | C12: West | D12: Ramesh | E12: Laptop | F12: 13 | G12: 55000 | H12: =F12*G12 -> 715000 | I12: =H12*VLOOKUP(E12,Lookup!$A$2:$C$7,3,FALSE()) -> 500500 | J12: =H12-I12 -> 214500
A13: ORD-1011 | B13: 45678 | C13: East | D13: Priya | E13: Docking Station | F13: 12 | G13: 4200 | H13: =F13*G13 -> 50400 | I13: =H13*VLOOKUP(E13,Lookup!$A$2:$C$7,3,FALSE()) -> 34272 | J13: =H13-I13 -> 16128
... A91: ORD-1089 | B91: 45763 | C91: North | D91: Divya | E91: Webcam | F91: 11 | G91: 2200 | H91: =F91*G91 -> 24200 | I91: =H91*VLOOKUP(E91,Lookup!$A$2:$C$7,3,FALSE()) -> 14520 | J91: =H91-I91 -> 9680

Sheet Lookup
A1: Product | B1: Category | C1: Cost Ratio
A2: Laptop | B2: Computing | C2: 0.7
A3: Monitor | B3: Peripherals | C3: 0.65
A4: Keyboard | B4: Accessories | C4: 0.55
A5: Mouse | B5: Accessories | C5: 0.5
A6: Docking Station | B6: Peripherals | C6: 0.68
A7: Webcam | B7: Accessories | C7: 0.6
